openmodel/__init__.py
openmodel/base.py
openmodel/field_types.py
openmodel-0.1.0.dist-info/WHEEL
openmodel-0.1.0.dist-info/METADATA
openmodel-0.1.0.dist-info/RECORD
