Metadata-Version: 2.1
Name: openmodel
Version: 0.1.0
Summary: Universal Data Schemas
License: BSD-3-Clause
Author: Ken Van Haren
Author-email: kenvanharen@gmail.com
Requires-Python: >=3.7,<4.0
Classifier: License :: OSI Approved :: BSD License
Classifier: Programming Language :: Python :: 3
Classifier: Programming Language :: Python :: 3.7
Classifier: Programming Language :: Python :: 3.8
Classifier: Programming Language :: Python :: 3.9
Requires-Dist: PyYAML (>=5.4.1,<6.0.0)
